otsuvalidator/__init__.py
otsuvalidator/bases.py
otsuvalidator/converters.py
otsuvalidator/validators.py
otsuvalidator-2022.11.30.dist-info/LICENSE.txt
otsuvalidator-2022.11.30.dist-info/METADATA
otsuvalidator-2022.11.30.dist-info/WHEEL
otsuvalidator-2022.11.30.dist-info/top_level.txt
otsuvalidator-2022.11.30.dist-info/RECORD
