Metadata-Version: 2.1
Name: otsuvalidator
Version: 2022.11.30
Summary: 単体でもディスクリプタとしても使用できるバリデータライブラリ
Home-page: https://github.com/Otsuhachi/OtsuValidator
Author: Otsuhachi
Author-email: agequodagis.tufuiegoeris@gmail.com
License: MIT License
Keywords: Python validator descriptor converter
License-File: LICENSE.txt
